MANIFEST.in
README.rst
requirements-test.txt
requirements.txt
setup.cfg
setup.py
conff/__init__.py
conff/ee.py
conff/parser.py
conff/test_parser.py
conff/utils.py
conff.egg-info/PKG-INFO
conff.egg-info/SOURCES.txt
conff.egg-info/dependency_links.txt
conff.egg-info/requires.txt
conff.egg-info/top_level.txt
conff/data/malformed_foreach_01.yml
conff/data/malformed_foreach_02.yml
conff/data/sample_config_01.yml
conff/data/sample_config_02.yml
conff/data/sample_config_03.yml
conff/data/test_config_01.yml
conff/data/test_config_02.yml
conff/data/test_config_03.yml
conff/data/test_config_04.yml
conff/data/test_config_05.yml