Metadata-Version: 1.2
Name: conff
Version: 0.5.0
Summary: Simple config parser with evaluator library.
Home-page: https://github.com/kororo/conff
Author: Robertus Johansyah
Author-email: kororola@gmail.com
License: UNKNOWN
Download-URL: https://github.com/kororo/conff/tarball/0.5.0
Keywords: config,parser,expression,parse,eval
Platform: UNKNOWN
Classifier: Intended Audience :: Developers
Classifier: License :: OSI Approved :: MIT License
Classifier: Natural Language :: English
Classifier: Operating System :: MacOS :: MacOS X
Classifier: Operating System :: POSIX
Classifier: Operating System :: POSIX :: BSD
Classifier: Operating System :: POSIX :: Linux
Classifier: Operating System :: Microsoft :: Windows
Classifier: Programming Language :: Python
Classifier: Programming Language :: Python :: 3.5
Classifier: Programming Language :: Python :: 3.6
Classifier: Topic :: Software Development :: Libraries :: Python Modules
Classifier: Programming Language :: Python
Requires-Python: >=3.5
